CHANGELOG.txt
LICENCE.txt
MANIFEST.in
README.txt
setup.py
examples/dags/dag_1.py
examples/dags/dag_2.py
torch_airflow/__init__.py
torch_airflow/dag.py
torch_airflow/initialiser.py
torch_airflow.egg-info/PKG-INFO
torch_airflow.egg-info/SOURCES.txt
torch_airflow.egg-info/dependency_links.txt
torch_airflow.egg-info/requires.txt
torch_airflow.egg-info/top_level.txt
torch_airflow/operators/__init__.py
torch_airflow/operators/span_operator.py
torch_airflow/utils/__init__.py
torch_airflow/utils/callback.py
torch_airflow/utils/pipeline.py